README.md
py_shotgun.py
setup.py
py_shotgun.egg-info/PKG-INFO
py_shotgun.egg-info/SOURCES.txt
py_shotgun.egg-info/dependency_links.txt
py_shotgun.egg-info/top_level.txt