Metadata-Version: 2.1
Name: py-shotgun
Version: 0.0.10
Summary: simple shotgun api wrap
Home-page: https://https://github.com/MoonShineVFX/py_shotgun
Author: Noflame Lin
Author-email: linjuang@gmail.com
License: UNKNOWN
Platform: UNKNOWN
Classifier: Programming Language :: Python :: 3
Classifier: License :: OSI Approved :: MIT License
Classifier: Operating System :: OS Independent
Requires-Python: >=3.6
